convex_api/__init__.py
convex_api/account.py
convex_api/api.py
convex_api/contract.py
convex_api/exceptions.py
convex_api/key_pair.py
convex_api/models.py
convex_api/py.typed
convex_api/registry.py
convex_api/tool/__init__.py
convex_api/tool/convex_tool.py
convex_api/tool/output.py
convex_api/tool/command/__init__.py
convex_api/tool/command/account_balance_command.py
convex_api/tool/command/account_command.py
convex_api/tool/command/account_create_command.py
convex_api/tool/command/account_fund_command.py
convex_api/tool/command/account_info_command.py
convex_api/tool/command/account_name_register_command.py
convex_api/tool/command/account_name_resolve_command.py
convex_api/tool/command/account_topup_command.py
convex_api/tool/command/argparse_typing.py
convex_api/tool/command/command_base.py
convex_api/tool/command/help_command.py
convex_api/tool/command/peer_command.py
convex_api/tool/command/peer_create_command.py
convex_api/tool/command/query_command.py
convex_api/tool/command/submit_command.py
convex_api_py-0.3.1.data/scripts/convex_tools.py
tests/__init__.py
tests/conftest.py
tests/types.py
tests/intergration/__init__.py
tests/intergration/test_account_api.py
tests/intergration/test_api.py
tests/intergration/test_basic_api.py
tests/intergration/test_contract.py
tests/intergration/test_convex_break.py
tests/intergration/test_convex_multi_thread.py
tests/intergration/tool/__init__.py
tests/intergration/tool/test_account_command.py
tests/intergration/tool/test_query_command.py
tests/intergration/tool/test_submit_comand.py
tests/unit/__init__.py
tests/unit/test_account.py
tests/unit/test_key_pair.py
convex_api_py-0.3.1.dist-info/LICENSE
convex_api_py-0.3.1.dist-info/METADATA
convex_api_py-0.3.1.dist-info/WHEEL
convex_api_py-0.3.1.dist-info/top_level.txt
convex_api_py-0.3.1.dist-info/RECORD
